flet_onesignal/__init__.py
flet_onesignal/flet_onesignal.py
flet_onesignal/languages.py
flet_onesignal-0.3.3.dist-info/licenses/LICENSE
flutter/flet_onesignal/CHANGELOG.md
flutter/flet_onesignal/LICENSE
flutter/flet_onesignal/README.md
flutter/flet_onesignal/analysis_options.yaml
flutter/flet_onesignal/flet_onesignal.iml
flutter/flet_onesignal/pubspec.lock
flutter/flet_onesignal/pubspec.yaml
flutter/flet_onesignal/build/last_build_run.json
flutter/flet_onesignal/build/a537d409f8a408aafab5ce76764b9432/_composite.stamp
flutter/flet_onesignal/build/a537d409f8a408aafab5ce76764b9432/gen_dart_plugin_registrant.stamp
flutter/flet_onesignal/build/a537d409f8a408aafab5ce76764b9432/gen_localizations.stamp
flutter/flet_onesignal/lib/flet_onesignal.dart
flutter/flet_onesignal/lib/src/create_control.dart
flutter/flet_onesignal/lib/src/flet_onesignal.dart
flutter/flet_onesignal/lib/src/utils/funcs.dart
flet_onesignal-0.3.3.dist-info/METADATA
flet_onesignal-0.3.3.dist-info/WHEEL
flet_onesignal-0.3.3.dist-info/top_level.txt
flet_onesignal-0.3.3.dist-info/RECORD
