Metadata-Version: 2.4
Name: flet-onesignal
Version: 0.3.3
Summary: Flutter OneSignal package integration for Python Flet.
Author-email: brunobrown <brunobrown.86@gmail.com>
License-Expression: MIT
Project-URL: Homepage, https://github.com/brunobrown/flet-onesignal
Project-URL: Repository, https://github.com/brunobrown/flet-onesignal
Project-URL: Issues, https://github.com/brunobrown/flet-onesignal/issues
Classifier: Topic :: Software Development :: Debuggers
Classifier: Intended Audience :: Developers
Classifier: Natural Language :: English
Classifier: Natural Language :: Portuguese (Brazilian)
Classifier: Operating System :: OS Independent
Classifier: Development Status :: 5 - Production/Stable
Classifier: Programming Language :: Python :: 3.9
Classifier: Programming Language :: Python :: 3.10
Classifier: Programming Language :: Python :: 3.11
Classifier: Programming Language :: Python :: 3.12
Classifier: Programming Language :: Python :: 3.13
Requires-Python: >=3.9
License-File: LICENSE
Requires-Dist: flet>=0.26.0
Dynamic: license-file
